pyDEER/__init__.py
pyDEER/awg.py
pyDEER/elexsys.py
pyDEER/tikreg.py
pyDEER-1.0.7.dist-info/LICENSE.txt
pyDEER-1.0.7.dist-info/METADATA
pyDEER-1.0.7.dist-info/WHEEL
pyDEER-1.0.7.dist-info/top_level.txt
pyDEER-1.0.7.dist-info/RECORD
