Metadata-Version: 2.1
Name: pyDEER
Version: 1.0.7
Summary: A Python Package for Processing Double Electron-Electron Resonance (DEER) Data
Home-page: https://github.com/tkellerBridge12/pyDEER
Author: Timothy Keller
Author-email: tkeller@bridge12.com
License: UNKNOWN
Project-URL: Source Code, https://github.com/tkellerBridge12/pyDEER
Project-URL: Documentation, https://pydeer.readthedocs.io/
Platform: UNKNOWN
Classifier: Programming Language :: Python :: 3
Classifier: License :: OSI Approved :: MIT License
Classifier: Operating System :: OS Independent
Requires-Python: >=2.6, >=3.6
Requires-Dist: scipy
Requires-Dist: numpy
